mannaggia/__init__.py
mannaggia/__main__.py
mannaggia/stats.py
mannaggia/santi/__init__.py
mannaggia/santi/factory.py
mannaggia/santi/santo.py
mannaggia/santi/api/__init__.py
mannaggia/santi/api/client.py
mannaggia/santi/api/santiebeati.py
mannaggia/speech/__init__.py
mannaggia/speech/espeak.py
mannaggia/speech/google_translate.py
mannaggia/speech/ispeech.py
mannaggia/speech/macos_say.py
mannaggia/speech/mozilla.py
mannaggia/speech/speaker.py
mannaggia/speech/tts.py
mannaggia-0.1.4.dist-info/LICENSE
mannaggia-0.1.4.dist-info/METADATA
mannaggia-0.1.4.dist-info/WHEEL
mannaggia-0.1.4.dist-info/entry_points.txt
mannaggia-0.1.4.dist-info/top_level.txt
mannaggia-0.1.4.dist-info/RECORD
