Metadata-Version: 2.1
Name: mannaggia
Version: 0.1.4
Summary: mannaggia is a python application to praise or more likely to curse the saints.
Home-page: https://github.com/veeso/mannaggia-py
Author: Christian veeso Visintin
Author-email: christian.visintin1997@gmail.com
License: WTFPL
Keywords: mannaggia,debugging-tools,italian-debugging-tool
Platform: UNKNOWN
Classifier: Development Status :: 5 - Production/Stable
Classifier: Intended Audience :: Developers
Classifier: Intended Audience :: End Users/Desktop
Classifier: Programming Language :: Python :: 3
Classifier: Operating System :: OS Independent
Classifier: Programming Language :: Python :: 3
Classifier: Programming Language :: Python :: 3.5
Requires-Python: >=3.5
Requires-Dist: appdirs (>=1.4.0)
Requires-Dist: click (>=8.0.0)
Requires-Dist: pathlib2 (>=2)
Requires-Dist: pydub (>=0.20.0)
Requires-Dist: requests (>=2.20.0)
Requires-Dist: simpleaudio (>=1.0.0)
